{"is_source_file": true, "format": "TypeScript (TSX)", "description": "This file is a React-like component written with Qwik framework, defining a layout component that includes styling and a slot for nested content, along with a request handler for caching configuration.", "external_files": ["./styles.css"], "external_methods": ["cacheControl"], "published": ["onGet", "default"], "classes": [], "methods": [{"name": "onGet", "description": "Request handler configuring cache control headers with cache duration settings."}, {"name": "default", "description": "Default exported Qwik component that applies styles and renders a main section with a slot for nested content."}], "calls": ["cacheControl", "useStyles$", "component$", "Slot"], "search-terms": ["layout", "Qwik", "RequestHandler", "cacheControl", "styles.css", "Slot", "component$"], "state": 2, "file_id": 12, "knowledge_revision": 33, "git_revision": "1fbd7a287a08621a5a22af819741cf8d07f1795e", "ctags": [], "hash": "0035d77763096cd2cb6b319870783c62", "format-version": 4, "code-base-name": "tic_tac_toe_frontend", "filename": "tic_tac_toe_frontend/src/routes/layout.tsx", "revision_history": [{"33": "1fbd7a287a08621a5a22af819741cf8d07f1795e"}]}